{
  "persons": [
    {
      "name": "Arto Hellas",
      "number": "040-123456",
      "id": 1
    },
    {
      "name": "Ada Lovelace",
      "number": "39-44-5323523",
      "id": 2
    },
    {
      "name": "Dan Abramov",
      "number": "12-43-234345",
      "id": 3
    },
    {
      "name": "Mary Poppendieck",
      "number": "39-23-6423122",
      "id": 4
    },
    {
      "id": 5,
      "name": "New name",
      "number": "564106"
    },
    {
      "id": 6,
      "name": "Marco Burman",
      "number": "07792527002"
    },
    {
      "id": 7,
      "name": "Test Person",
      "number": "668011016"
    },
    {
      "id": 8,
      "name": "Don't Error",
      "number": "999"
    },
    {
      "id": 9,
      "name": "Step 7",
      "number": "0181 995 3517"
    },
    {
      "id": 10,
      "name": "Response Test",
      "number": "707898985"
    },
    {
      "id": 11,
      "name": "Axios Refactor",
      "number": "18-48-335101"
    },
    {
      "name": "ID Test",
      "number": "80-18-66510",
      "id": 12
    },
    {
      "id": 13,
      "name": "Re-render Test",
      "number": "90-10-616810"
    },
    {
      "id": 14,
      "name": "Re-render No Highlight",
      "number": "91-10-66101"
    }
  ]
}